Workbook

Sheet Identification
A1: ARCEP Gabon — Module M14 · Gabarit de collecte N0 (OP-MM · mensuel)
A2: Document opposable — décision ARCEP fixant les gabarits (REF-06). Niveau N0 : données déclarées.
A4: Opérateur / EME | B4: Exemple SA
A5: Identifiant ARCEP | B5: GA-OP-000
A6: Période déclarée (mois, AAAA-MM) | B6: 2026-07
A7: Date de dépôt (AAAA-MM-JJ) | B7: 2026-08-15
A8: Nom et fonction du déclarant | B8: A. NDONG — Directeur régulation
A9: Courriel du déclarant | B9: declarant@exemple.ga
A10: Téléphone du déclarant | B10: +241 06 00 00 00
A12: Rappels réglementaires :
A13: • Le dépôt s'effectue sur le portail ARCEP (SSO) accompagné du manifeste signé (hash SHA-256 du fichier) — EX-L2-01.
A14: • Toute cellule jaune non renseignée doit être justifiée en commentaire ; un lot incomplet peut être rejeté (EX-L2-02).
A15: • Les valeurs déclarées portent le drapeau « déclaré » et sont recoupées par les mesures indépendantes de l'ARCEP (N3) ;
A16: • tout écart au-delà des seuils du dictionnaire L4 déclenche la procédure contradictoire (L3.5 / L10).
A17: • Aucune donnée nominative ne doit figurer dans ce gabarit (loi n°001/2011).
A19: Légende :
B20: Cellule JAUNE : à renseigner par le déclarant.
B21: Cellule ORANGÉE : exemple de format — à remplacer par vos valeurs réelles.
B22: Cellule BLEUE : calcul automatique — ne pas modifier.

Sheet MU_Comptes
A1: Comptes DFS par province — indicateurs MU-01 / MU-02
A2: MU-01 : comptes enregistrés (cumul fin de période). MU-02 : comptes avec ≥ 1 opération sur 90 jours.
A4: Province | B4: Comptes enregistrés (cumul) | C4: Comptes actifs 90 jours
A5: Estuaire | B5: 512340 | C5: 287100
A6: Haut-Ogooué
A7: Moyen-Ogooué
A8: Ngounié
A9: Nyanga
A10: Ogooué-Ivindo
A11: Ogooué-Lolo
A12: Ogooué-Maritime
A13: Woleu-Ntem
A14: TOTAL NATIONAL | B14: =SUM(B5:B13) -> 512340 | C14: =SUM(C5:C13) -> 287100

Sheet MU_Transactions
A1: Transactions par type — indicateurs MU-03 / MU-04 / MU-06
A2: Nombre et valeur (XAF) des opérations abouties sur la période. P2P inter-réseaux = MU-06.
A4: Type d'opération | B4: Nombre d'opérations | C4: Valeur totale (XAF) | D4: Frais clients perçus (XAF) — CT-04
A5: Dépôt (cash-in) | B5: 1250000 | C5: 18750000000 | D5: 187500000
A6: Retrait (cash-out)
A7: P2P intra-réseau
A8: P2P inter-réseaux
A9: Paiement marchand
A10: Paiement de facture
A11: Recharge de crédit
A12: Transfert international
A13: TOTAL | B13: =SUM(B5:B12) -> 1250000 | C13: =SUM(C5:C12) -> 18750000000 | D13: =SUM(D5:D12) -> 187500000
A15: Répartition par canal d'initiation — indicateur MU-08 (nombre d'opérations)
A16: Canal | B16: Nombre d'opérations
A17: USSD | B17: 1250000
A18: STK (SIM Toolkit)
A19: Application mobile
A20: API (PSP tiers)
A21: SMS
A22: TOTAL (doit égaler le total des opérations) | B22: =SUM(B17:B21) -> 1250000

Sheet QS_Qualite
A1: Qualité et disponibilité déclarées par canal — QS-01 (déclaré) / QS-09 / QS-10
A2: Ces valeurs déclarées sont comparées aux mesures indépendantes (QS-11) ; écart > 1 point → contradictoire.
A4: Canal | B4: Disponibilité déclarée (%) | C4: Nb incidents majeurs (indispo > 30 min) | D4: Durée cumulée d'indisponibilité (minutes) | E4: MTTR (minutes) — calcul | F4: Taux de succès transactionnel déclaré (%)
A5: USSD | B5: 0.9945 | C5: 2 | D5: 145 | E5: =IF(N(C5)=0,"—",D5/C5) -> 72.5 | F5: 0.972
A6: STK (SIM Toolkit) | E6: =IF(N(C6)=0,"—",D6/C6) -> —
A7: Application mobile | E7: =IF(N(C7)=0,"—",D7/C7) -> —
A8: API (PSP tiers) | E8: =IF(N(C8)=0,"—",D8/C8) -> —
A9: SMS | E9: =IF(N(C9)=0,"—",D9/C9) -> —

Sheet RD_Distribution
A1: Réseau de distribution par province — RD-01
A2: Point actif = ≥ 1 opération sur les 30 derniers jours. Le registre géolocalisé détaillé est déposé dans l'onglet Points_de_service.
A4: Province | B4: Points de service déclarés | C4: Points de service actifs (30 j)
A5: Estuaire | B5: 2140 | C5: 1830
A6: Haut-Ogooué
A7: Moyen-Ogooué
A8: Ngounié
A9: Nyanga
A10: Ogooué-Ivindo
A11: Ogooué-Lolo
A12: Ogooué-Maritime
A13: Woleu-Ntem
A14: TOTAL NATIONAL | B14: =SUM(B5:B13) -> 2140 | C14: =SUM(C5:C13) -> 1830

Sheet Points_de_service
A1: Registre géolocalisé des points de service — support de RD-03 et de l'échantillonnage des campagnes mystères
A2: Une ligne par point. Identifiant professionnel uniquement — aucune donnée nominative (pas de nom de personne physique).
A4: Identifiant point (interne opérateur) | B4: Province | C4: Ville / localité | D4: Latitude (degrés décimaux) | E4: Longitude (degrés décimaux) | F4: Statut (ACTIF / INACTIF) | G4: Date de dernière activité (AAAA-MM-JJ)
A5: AGT-LBV-00421 | B5: Estuaire | C5: Libreville — Nzeng-Ayong | D5: 0.4162 | E5: 9.4673 | F5: ACTIF | G5: 2026-07-28
A13: … ajouter autant de lignes que de points de service (ou joindre un CSV au même schéma).

Sheet CT_Tarifs
A1: Grille tarifaire en vigueur — CT-01 (et base de contrôle CT-02)
A2: La grille déposée fait foi pour le contrôle des frais réellement appliqués (mesures N3). Tout écart constaté ouvre un contradictoire (tolérance zéro).
A4: Type d'opération | B4: Palier — montant min (XAF) | C4: Palier — montant max (XAF) | D4: Frais fixes (XAF) | E4: Frais proportionnels (%) | F4: Date d'application (AAAA-MM-JJ) | G4: Date de dépôt à l'ARCEP (AAAA-MM-JJ)
A5: P2P intra-réseau | B5: 1000 | C5: 5000 | D5: 100 | E5: 0 | F5: 2026-01-01 | G5: 2025-12-10
A15: … une ligne par type et par palier. Les frais proportionnels sont saisis en fraction (0,01 = 1 %).

Sheet RC_Reclamations
A1: Réclamations consommateurs par motif — RC-01 / RC-02 / RC-03 / RC-04
A2: Réclamations DFS reçues par vos canaux de service client sur la période.
A4: Motif | B4: Reçues | C4: Closes | D4: Délai médian de traitement (jours) | E4: Closes au premier contact | F4: Escaladées à l'ARCEP
A5: Transaction échouée non remboursée | B5: 1240 | C5: 1180 | D5: 3.5 | E5: 890 | F5: 12
A6: Frais contestés
A7: Accès au compte / fraude alléguée
A8: Agent / point de service
A9: Qualité du canal (USSD, application)
A10: Autre
A11: TOTAL | B11: =SUM(B5:B10) -> 1240 | C11: =SUM(C5:C10) -> 1180 | E11: =SUM(E5:E10) -> 890 | F11: =SUM(F5:F10) -> 12

Sheet Contrôles
A1: Contrôles de cohérence automatiques
A2: Tous les contrôles doivent afficher OK avant dépôt. Ne rien saisir dans cette feuille.
A4: Contrôle | B4: Résultat
A5: Comptes actifs ≤ comptes enregistrés, pour chaque province (MU_Comptes) | B5: =IF(SUMPRODUCT(--(MU_Comptes!C5:C13>MU_Comptes!B5:B13))=0,"OK","À corriger") -> OK
A6: Répartition par canal (MU-08) = total des opérations (MU-03) | B6: =IF(N(MU_Transactions!B22)=N(MU_Transactions!B13),"OK","À corriger") -> OK
A7: Disponibilités déclarées comprises entre 90 % et 100 % (QS_Qualite) | B7: =IF(SUMPRODUCT(--(QS_Qualite!B5:B9>1))+SUMPRODUCT(--((QS_Qualite!B5:B9<0.9)*(QS_Qualite!B5:B9<>0)))=0,"OK","À corriger") -> OK
A8: Points actifs ≤ points déclarés, pour chaque province (RD_Distribution) | B8: =IF(SUMPRODUCT(--(RD_Distribution!C5:C13>RD_Distribution!B5:B13))=0,"OK","À corriger") -> OK
A9: Réclamations closes ≤ reçues, pour chaque motif (RC_Reclamations) | B9: =IF(SUMPRODUCT(--(RC_Reclamations!C5:C10>RC_Reclamations!B5:B10))=0,"OK","À corriger") -> OK
A10: Closes au premier contact ≤ closes, pour chaque motif (RC_Reclamations) | B10: =IF(SUMPRODUCT(--(RC_Reclamations!E5:E10>RC_Reclamations!C5:C10))=0,"OK","À corriger") -> OK
A12: SYNTHÈSE — le gabarit est-il cohérent ? | B12: =IF(COUNTIF(B5:B10,"À corriger")=0,"OK","À corriger") -> OK
